stinger_python_utils/__init__.py
stinger_python_utils/message_creator.py
stinger_python_utils/return_codes.py
stinger_python_utils-0.1.3.dist-info/METADATA
stinger_python_utils-0.1.3.dist-info/WHEEL
stinger_python_utils-0.1.3.dist-info/licenses/LICENSE
stinger_python_utils-0.1.3.dist-info/RECORD
