Metadata-Version: 2.4
Name: stinger-python-utils
Version: 0.1.3
Summary: Common utilities for Stinger Python services.
License-Expression: MIT
License-File: LICENSE
Requires-Python: >=3.7
Requires-Dist: pydantic>=2.5.3
Requires-Dist: pyqttier>=0.2.0
